{
	"layout.navbar.media": "layout.navbar.media",
	"layout.navbar.events": "layout.navbar.events",
	"layout.navbar.about": "layout.navbar.about",
	"layout.navbar.history": "layout.navbar.history",
	"layout.navbar.conductor": "layout.navbar.conductor",
	"layout.navbar.musicians": "layout.navbar.musicians",
	"layout.navbar.artists": "layout.navbar.artists",
	"layout.navbar.composers": "layout.navbar.composers",
	"layout.navbar.archive": "layout.navbar.archive",
	"layout.navbar.photos": "layout.navbar.photos",
	"layout.navbar.videos": "layout.navbar.videos",
	"layout.navbar.contacts": "layout.navbar.contacts",
	"layout.navbar.partners": "layout.navbar.partners"
}